src/raccoonai_mcp_server/__init__.py
src/raccoonai_mcp_server/__main__.py
src/raccoonai_mcp_server/server.py
orange_raccoonai_mcp_server-0.0.1.dist-info/METADATA
orange_raccoonai_mcp_server-0.0.1.dist-info/WHEEL
orange_raccoonai_mcp_server-0.0.1.dist-info/RECORD
