Metadata-Version: 2.4
Name: orange-raccoonai-mcp-server
Version: 0.0.1
Summary: A MCP server for Raccoon AI LAM API
Author: Raccoon AI
Maintainer-email: scorchy38 <shubh@flyingraccoon.tech>
Classifier: Intended Audience :: Developers
Classifier: License :: OSI Approved :: MIT License
Classifier: Programming Language :: Python :: 3
Classifier: Programming Language :: Python :: 3.10
Requires-Python: >=3.10
Requires-Dist: mcp[cli]>=1.3.0
Requires-Dist: raccoonai>=0.1.0a10
